biodataplot/__init__.py
biodataplot/common.py
biodataplot/genomeview.py
biodataplot/metaplot.py
biodataplot/sequence.py
biodataplot/utils.py
biodataplot-0.0.4.dist-info/METADATA
biodataplot-0.0.4.dist-info/WHEEL
biodataplot-0.0.4.dist-info/top_level.txt
biodataplot-0.0.4.dist-info/RECORD
